{
  "dataVariables": "LanguageDataVariables",
  "readListAction": "readCities",
  "deleteDataAction": "deleteCity",
  "reduxDataListState": "state.template?.masterData?.languages",
  "reduxPaginationData": "state.template?.masterData?.languages?.pagination",
  "tableHeadersPath": "tableHeadersLanguages",
  "filterConfig": "cityFilters",
  "updateData": "updateCity",
  "createData": "createCity",
  "showData": "showCity",
  "newPath": "NewCity",
  "viewPath": "ViewCity",
  "updatePath": "UpdateCity",
  "listPath": "Cities",
  "reduxSelectedData": "state.state.selectedCity"
}
